donut_cli.py
donut_cli-0.1.8.1.dist-info/METADATA
donut_cli-0.1.8.1.dist-info/WHEEL
donut_cli-0.1.8.1.dist-info/entry_points.txt
donut_cli-0.1.8.1.dist-info/top_level.txt
donut_cli-0.1.8.1.dist-info/RECORD
